retro_dos_border_ui/__init__.py
retro_dos_border_ui/retro_ui.py
retro_dos_border_ui-0.1.4.dist-info/licenses/LICENSE
retro_dos_border_ui-0.1.4.dist-info/METADATA
retro_dos_border_ui-0.1.4.dist-info/WHEEL
retro_dos_border_ui-0.1.4.dist-info/top_level.txt
retro_dos_border_ui-0.1.4.dist-info/RECORD
