Metadata-Version: 2.4
Name: retro-dos-border-ui
Version: 0.1.4
Summary: A retro DOS-style console UI library using curses.
Home-page: https://github.com/markovanderpuil/retro-dos-border-ui
Author: Marko van der Puil
Classifier: Programming Language :: Python :: 3
Classifier: License :: OSI Approved :: MIT License
Classifier: Operating System :: OS Independent
Requires-Python: >=3.6
License-File: LICENSE
Dynamic: author
Dynamic: classifier
Dynamic: home-page
Dynamic: license-file
Dynamic: requires-python
Dynamic: summary
